Workbook

Sheet README
A1: SolarAlign model workbook
A3: What this is | B3: One linked workbook that mirrors src/lib/scheduleModel.ts. Inputs and PVWatts data feed yearly cash flows, which feed the summary. Change an input and every sheet updates.
A4: Flow | B4: PVWatts (monthly kWh) -> Inputs (annual kWh, costs, rates) -> CashFlows (years 0-30, three schedules + baseline) -> Summary (NPV, break-even, owner vs tenant).
A5: Sheets | B5: Summary: results and checks. Inputs: every number with status, source and link. PVWatts: the real production data. CashFlows: the yearly math. Reference: primary figures behind the sourced inputs.
A6: Colors | B6: Blue = hardcoded value. Black = formula. Green = pulled from another sheet. Yellow = replace with a confirmed value (roof cost, roof year, removal cost) or edit the owner-share scenarios.
A7: Method | B7: Incremental NPV = NPV(schedule) - NPV(roof-only baseline). Time 0 = today; a project installed at time s pays at s and produces from year s+1; discounting uses a REAL discount rate, so escalation is a real growth rate.
A8: Honest limits | B8: Roof cost, roof year, removal cost, downtime, owner share and escalation are assumed. The electricity price is a single-month commercial average (a ceiling). No incentives, no structural approval, no legal eligibility for tenant credits. Synthetic property.
A9: Link to the code | B9: Inputs mirror data/assumptions.json. Results should match npm run schedules. If you change values here, change them in the JSON too.

Sheet Summary
A1: Results: three roof/solar schedules vs roof-only baseline
A2: Everything here is a formula. Change Inputs (or the owner-share row below) and it updates. Synthetic property; roof inputs are assumed until confirmed.
A5: Schedule | B5: Incremental owner NPV | C5: PV solar capex | D5: PV O&M | E5: PV removal / reinstall | F5: Roof timing penalty | G5: PV electricity value to owner | H5: PV electricity value to tenants | I5: Total PV electricity value
A6: A: Solar now, remove & reinstall later | B6: =CashFlows!K36-CashFlows!E36 -> 383980.21 | C6: =CashFlows!F36 -> 1065000 | D6: =CashFlows!G36 -> 124599.22 | E6: =CashFlows!H36 -> 61566.931 | F6: =CashFlows!I36-CashFlows!D36 -> 0 | G6: =Inputs!$B$18*CashFlows!J36 -> 1635146.4 | H6: =(1-Inputs!$B$18)*CashFlows!J36 -> 0 | I6: =CashFlows!J36 -> 1635146.4
A7: B: Replace roof now + solar now | B7: =CashFlows!Q36-CashFlows!E36 -> 375976.79 | C7: =CashFlows!L36 -> 1065000 | D7: =CashFlows!M36 -> 124599.22 | E7: =CashFlows!N36 -> 0 | F7: =CashFlows!O36-CashFlows!D36 -> 89553.793 | G7: =Inputs!$B$18*CashFlows!P36 -> 1655129.8 | H7: =(1-Inputs!$B$18)*CashFlows!P36 -> 0 | I7: =CashFlows!P36 -> 1655129.8
A8: C: Replace roof at planned time + solar then | B8: =CashFlows!W36-CashFlows!E36 -> 323378.96 | C8: =CashFlows!R36 -> 874250.42 | D8: =CashFlows!S36 -> 96942.9 | E8: =CashFlows!T36 -> 0 | F8: =CashFlows!U36-CashFlows!D36 -> 0 | G8: =Inputs!$B$18*CashFlows!V36 -> 1294572.3 | H8: =(1-Inputs!$B$18)*CashFlows!V36 -> 0 | I8: =CashFlows!V36 -> 1294572.3
A9: Roof-only baseline NPV | B9: =CashFlows!E36 -> -410446.21
A10: Owner share of electricity value (from Inputs) | B10: =Inputs!$B$18 -> 1
A11: Best schedule for the owner | B11: =INDEX(A6:A8,MATCH(MAX(B6:B8),B6:B8,0)) -> A: Solar now, remove & reinstall later
A13: Break-even removal/reinstall cost for schedule A
A14: vs doing nothing (NPV = 0) | B14: =IF(Inputs!$B$16+B6/INDEX(CashFlows!$B$5:$B$35,Inputs!$B$15+1)>=0,Inputs!$B$16+B6/INDEX(CashFlows!$B$5:$B$35,Inputs!$B$15+1),"n/a") -> 542759.49
A15: vs best alternative (B or C) | B15: =IF(Inputs!$B$16+(B6-MAX(B7,B8))/INDEX(CashFlows!$B$5:$B$35,Inputs!$B$15+1)>=0,Inputs!$B$16+(B6-MAX(B7,B8))/INDEX(CashFlows!$B$5:$B$35,Inputs!$B$15+1),"never wins") -> 84749.663
A17: Owner NPV by owner share (same solar production in every column)
A18: Schedule / owner share of electricity value | B18: 1 | C18: 0.7 | D18: 0.4 | E18: 0
A19: A: Solar now, remove & reinstall later | B19: =B$18*$I6-$C6-$D6-$E6-$F6 -> 383980.21 | C19: =C$18*$I6-$C6-$D6-$E6-$F6 -> -106563.69 | D19: =D$18*$I6-$C6-$D6-$E6-$F6 -> -597107.6 | E19: =E$18*$I6-$C6-$D6-$E6-$F6 -> -1251166.1
A20: B: Replace roof now + solar now | B20: =B$18*$I7-$C7-$D7-$E7-$F7 -> 375976.79 | C20: =C$18*$I7-$C7-$D7-$E7-$F7 -> -120562.15 | D20: =D$18*$I7-$C7-$D7-$E7-$F7 -> -617101.09 | E20: =E$18*$I7-$C7-$D7-$E7-$F7 -> -1279153
A21: C: Replace roof at planned time + solar then | B21: =B$18*$I8-$C8-$D8-$E8-$F8 -> 323378.96 | C21: =C$18*$I8-$C8-$D8-$E8-$F8 -> -64992.723 | D21: =D$18*$I8-$C8-$D8-$E8-$F8 -> -453364.41 | E21: =E$18*$I8-$C8-$D8-$E8-$F8 -> -971193.32
A23: Electricity value that goes to tenants (present value)
A24: A: Solar now, remove & reinstall later | B24: =(1-B$18)*$I6 -> 0 | C24: =(1-C$18)*$I6 -> 490543.91 | D24: =(1-D$18)*$I6 -> 981087.82 | E24: =(1-E$18)*$I6 -> 1635146.4
A25: B: Replace roof now + solar now | B25: =(1-B$18)*$I7 -> 0 | C25: =(1-C$18)*$I7 -> 496538.94 | D25: =(1-D$18)*$I7 -> 993077.88 | E25: =(1-E$18)*$I7 -> 1655129.8
A26: C: Replace roof at planned time + solar then | B26: =(1-B$18)*$I8 -> 0 | C26: =(1-C$18)*$I8 -> 388371.68 | D26: =(1-D$18)*$I8 -> 776743.37 | E26: =(1-E$18)*$I8 -> 1294572.3
A28: Checks
A29: Owner + tenant value = total value (all schedules) | B29: =IF(AND(ABS(G6+H6-I6)<0.01,ABS(G7+H7-I7)<0.01,ABS(G8+H8-I8)<0.01),"OK","CHECK") -> OK
A30: Owner-share table matches schedule results at current share | B30: =IF(AND(ABS(INDEX(B19:E19,1,MATCH(Inputs!$B$18,B18:E18,0))-B6)<0.01,ABS(INDEX(B20:E20,1,MATCH(Inputs!$B$18,B18:E18,0))-B7)<0.01,ABS(INDEX(B21:E21,1,MATCH(Inputs!$B$18,B18:E18,0))-B8)<0.01),"OK","n/a (share not in table)") -> OK
A31: Monthly PVWatts values add up to annual | B31: =PVWatts!B19 -> OK
A32: Roof year inside horizon | B32: =IF(AND(Inputs!$B$15>=1,Inputs!$B$15<=Inputs!$B$13,Inputs!$B$13<=30),"OK","CHECK") -> OK

Sheet Inputs
A1: Model inputs
A2: Blue = hardcoded value you can change. Green = pulled from another sheet. Yellow = replace with confirmed value (synthetic PCA report / quote).
A4: Input | B4: Value | C4: Unit | D4: Status | E4: Source | F4: Link | G4: Notes / caveats
A5: Annual AC production, year 1 | B5: =PVWatts!B17 -> 614383.45 | C5: kWh | D5: Sourced | E5: PVWatts V8 API response saved at fixtures/pvwatts_demo_property_a.json (outputs.ac_annual) | F5: https://developer.nlr.gov/docs/solar/pvwatts/v8/ | G5: NSRDB TMY-2020 weather; grid cell ~1.1 km from the input coordinates. Typical-year estimate, not a guarantee. Retrieved date = date the fixture was pulled; edit if different.
A6: System capacity | B6: 500 | C6: kW DC | D6: Assumed | E6: Input to the PVWatts request (system_capacity=500) | F6: https://developer.nlr.gov/docs/solar/pvwatts/v8/ | G6: Chosen value. Must be consistent with the synthetic PCA roof area (500 kW needs roughly 50,000 sq ft of usable roof).
A7: Electricity value (year 1) | B7: 0.2411 | C7: $/kWh | D7: Sourced | E7: EIA Electric Power Monthly Table 5.6.A (Aug 2026, preliminary): Massachusetts commercial average price = 24.11 cents/kWh | F7: https://www.eia.gov/electricity/monthly/xls/table_5_06_a.xlsx | G7: Single-month, all-commercial-customer average price. It includes demand and fixed charges, so treat it as a CEILING on what a solar kWh is worth. Aug 2025 (final) was 23.15 cents. U.S. commercial Aug 2026 was 14.47 cents. Test sensitivity on this input.
A8: Solar installed cost | B8: 2.13 | C8: $/W DC | D8: Sourced | E8: NREL/NLR TP-7A40-92536 (Jan 2025), Table A-1: commercial PV, 200 kWdc rooftop, Q1 2022 modeled market price, 2024 USD | F8: https://docs.nlr.gov/docs/fy25osti/92536.pdf | G8: Most recent rooftop-based benchmark in the report. The 2023-24 benchmarks switched to a 3 MWdc ground-mount ($1.55 in 2024), which is not comparable to a rooftop. Benchmarks are not local prices; get installer quotes. Roof upgrades and financing are not in the benchmark.
A9: O&M cost | B9: 21 | C9: $/kW-year | D9: Sourced | E9: NREL/NLR TP-7A40-92536, Table A-7: commercial PV O&M, 2022 (200 kWdc rooftop), $/kWdc-yr | F9: https://docs.nlr.gov/docs/fy25osti/92536.pdf | G9: 2024 value (3 MWdc ground-mount) is $20/kWdc-yr.
A10: Degradation rate | B10: 0.007 | C10: fraction per year | D10: Sourced | E10: NREL/NLR TP-7A40-92536, Table A-7: commercial PV annual degradation, 0.70% per year | F10: https://docs.nlr.gov/docs/fy25osti/92536.pdf | G10: Benchmark modeling assumption, not a measurement of a specific installation.
A11: Discount rate (REAL) | B11: 0.068 | C11: fraction per year | D11: Sourced | E11: NREL/NLR TP-7A40-92536, Table A-7: commercial PV equity discount rate (real), 6.8% for 2023-2024 (6.1% for 2022) | F11: https://docs.nlr.gov/docs/fy25osti/92536.pdf | G11: This is a REAL rate, so keep prices and costs in constant dollars and use a real escalation rate. An owner's own hurdle rate may differ. Low/high are an assumed sensitivity range.
A12: Electricity price escalation (REAL) | B12: 0 | C12: fraction per year | D12: Assumed | E12: Modeling choice: 0% real growth (constant real prices) | G12: Set to 0% because the discount rate is real. Use a positive value only as a real growth rate (above inflation), or switch the whole model to nominal terms. Disclose as assumed.
A13: Analysis horizon | B13: 25 | C13: years | D13: Assumed | E13: Modeling choice | G13: No end-of-horizon value is counted, so later installs get fewer producing years.
A14: Roof replacement cost | B14: 500000 | C14: $ | D14: Assumed | E14: To be replaced by the confirmed value from the synthetic PCA report | G14: Placeholder. Base the PCA figure on a roofing cost estimate (e.g. RSMeans or an installer rule of thumb) and label it assumed. Same cost in every schedule.
A15: Roof replacement year | B15: 3 | C15: year (1-25) | D15: Assumed | E15: To be replaced by the confirmed remaining-life range from the synthetic PCA report | G15: Placeholder is the midpoint of a 2-4 year remaining-life range.
A16: Panel removal/reinstall cost | B16: 75000 | C16: $ | D16: Assumed | E16: Placeholder until an installer quote exists | G16: Exposed as a slider in the app.
A17: Downtime during roof work | B17: 2 | C17: months (0-12) | D17: Assumed | E17: Placeholder until a roofer/installer estimate exists | G17: Only affects the 'solar now, remove later' schedule.
A18: Owner share of electricity value | B18: 1 | C18: fraction (0-1) | D18: Assumed | E18: Screen C switch (illustrative billing assumption) | G18: 1 = owner-controlled meter. Lower values send value to tenants. Not a legal eligibility determination.
A20: Sourced inputs | B20: =COUNTIF(D5:D18,"Sourced") -> 6
A21: Assumed inputs (label as assumed in the app) | B21: =COUNTIF(D5:D18,"Assumed") -> 8
A22: Max horizon this sheet supports is 30 years. discountRate is REAL, so escalation is a real growth rate. All property/roof/billing data is synthetic.

Sheet PVWatts
A1: PVWatts V8 output (fixtures/pvwatts_demo_property_a.json)
A2: Real data from the PVWatts API. Monthly AC production feeds the annual total, which feeds Inputs.
A4: Month | B4: AC production (kWh) | C4: DC production (kWh) | D4: Plane-of-array (kWh/m2) | E4: Solar radiation (kWh/m2/day)
A5: Jan | B5: 33409.966 | C5: 35223.456 | D5: 80.739061 | E5: 2.6044858
A6: Feb | B6: 39450.447 | C6: 41471.887 | D6: 95.838724 | E6: 3.4228116
A7: Mar | B7: 57495.12 | C7: 60351.789 | D7: 143.04334 | E7: 4.6143015
A8: Apr | B8: 60519.234 | C8: 63526.602 | D8: 157.93951 | E8: 5.2646502
A9: May | B9: 69783.565 | C9: 73257.318 | D9: 189.5478 | E9: 6.1144452
A10: Jun | B10: 65071.643 | C10: 68375.158 | D10: 179.45547 | E10: 5.981849
A11: Jul | B11: 71963.831 | C11: 75516.774 | D11: 201.61783 | E11: 6.5038011
A12: Aug | B12: 64392.588 | C12: 67613.428 | D12: 180.06223 | E12: 5.8084591
A13: Sep | B13: 54916.676 | C13: 57674.458 | D13: 148.98978 | E13: 4.9663259
A14: Oct | B14: 42668.218 | C14: 44923.938 | D14: 110.54687 | E14: 3.5660282
A15: Nov | B15: 30416.463 | C15: 32092.679 | D15: 75.208893 | E15: 2.5069631
A16: Dec | B16: 24295.693 | C16: 25754.947 | D16: 59.109338 | E16: 1.9067528
A17: Annual total (sum of months) | B17: =SUM(B5:B16) -> 614383.45 | C17: =SUM(C5:C16) -> 645782.43
A18: ac_annual reported by PVWatts | B18: 614383.45
A19: Check: months add up to annual | B19: =IF(ABS(B17-B18)<1,"OK","CHECK") -> OK
A20: Capacity factor (%) | B20: =B17/(Inputs!B6*8760) -> 0.14027019
A22: Request inputs and station
A23: system_capacity (kW) | B23: 500
A24: module_type | B24: 0
A25: losses (%) | B25: 14
A26: array_type (1 = fixed roof) | B26: 1
A27: tilt (deg) | B27: 10
A28: azimuth (deg) | B28: 180
A29: lat | B29: 42.36
A30: lon | B30: -71.06
A31: dataset | B31: nsrdb
A32: Weather source | B32: NSRDB PSM V3 GOES tmy-2020 3.2.0
A33: Distance to weather grid cell (m) | B33: 1117
A34: PVWatts version | B34: 8.5.0

Sheet CashFlows
A1: Yearly cash flows by schedule (time 0 = today)
A2: Costs are positive numbers. Owner net cash flow = owner share of electricity value minus capex, O&M, removal/reinstall and roof cost. Row 36 = present value.
D3: Roof-only baseline | F3: A: Solar now, remove & reinstall at roof replacement | L3: B: Replace roof now + solar now | R3: C: Replace roof at planned time + solar then
A4: Year t | B4: Discount factor | C4: In horizon (1/0) | D4: Roof cost | E4: Net cash flow | F4: Solar capex | G4: O&M | H4: Removal/ reinstall | I4: Roof cost | J4: Electricity value (total) | K4: Owner net cash flow | L4: Solar capex | M4: O&M | N4: Removal/ reinstall | O4: Roof cost | P4: Electricity value (total) | Q4: Owner net cash flow | R4: Solar capex | S4: O&M | T4: Removal/ reinstall | U4: Roof cost | V4: Electricity value (total) | W4: Owner net cash flow
A5: 0 | B5: =1/(1+Inputs!$B$11)^$A5 -> 1 | C5: =IF($A5<=Inputs!$B$13,1,0) -> 1 | D5: =$C5*IF($A5=Inputs!$B$15,Inputs!$B$14,0) -> 0 | E5: =-D5 -> 0 | F5: =$C5*IF($A5=0,Inputs!$B$8*Inputs!$B$6*1000,0) -> 1065000 | G5: =$C5*IF($A5>=1,Inputs!$B$9*Inputs!$B$6,0) -> 0 | H5: =$C5*IF($A5=Inputs!$B$15,Inputs!$B$16,0) -> 0 | I5: =$C5*IF($A5=Inputs!$B$15,Inputs!$B$14,0) -> 0 | J5: =$C5*IF($A5<1,0,Inputs!$B$5*(1-Inputs!$B$10)^($A5-1)*Inputs!$B$7*(1+Inputs!$B$12)^($A5-1)*(1-IF($A5=Inputs!$B$15,Inputs!$B$17/12,0))) -> 0 | K5: =J5*Inputs!$B$18-F5-G5-H5-I5 -> -1065000 | L5: =$C5*IF($A5=0,Inputs!$B$8*Inputs!$B$6*1000,0) -> 1065000 | M5: =$C5*IF($A5>=1,Inputs!$B$9*Inputs!$B$6,0) -> 0 | N5: =0 -> 0 | O5: =$C5*IF($A5=0,Inputs!$B$14,0) -> 500000 | P5: =$C5*IF($A5<1,0,Inputs!$B$5*(1-Inputs!$B$10)^($A5-1)*Inputs!$B$7*(1+Inputs!$B$12)^($A5-1)) -> 0 | Q5: =P5*Inputs!$B$18-L5-M5-N5-O5 -> -1565000 | R5: =$C5*IF($A5=Inputs!$B$15,Inputs!$B$8*Inputs!$B$6*1000,0) -> 0 | S5: =$C5*IF($A5>Inputs!$B$15,Inputs!$B$9*Inputs!$B$6,0) -> 0 | T5: =0 -> 0 | U5: =$C5*IF($A5=Inputs!$B$15,Inputs!$B$14,0) -> 0 | V5: =$C5*IF($A5<=Inputs!$B$15,0,Inputs!$B$5*(1-Inputs!$B$10)^($A5-Inputs!$B$15-1)*Inputs!$B$7*(1+Inputs!$B$12)^($A5-1)) -> 0 | W5: =V5*Inputs!$B$18-R5-S5-T5-U5 -> 0
A6: 1 | B6: =1/(1+Inputs!$B$11)^$A6 -> 0.93632959 | C6: =IF($A6<=Inputs!$B$13,1,0) -> 1 | D6: =$C6*IF($A6=Inputs!$B$15,Inputs!$B$14,0) -> 0 | E6: =-D6 -> 0 | F6: =$C6*IF($A6=0,Inputs!$B$8*Inputs!$B$6*1000,0) -> 0 | G6: =$C6*IF($A6>=1,Inputs!$B$9*Inputs!$B$6,0) -> 10500 | H6: =$C6*IF($A6=Inputs!$B$15,Inputs!$B$16,0) -> 0 | I6: =$C6*IF($A6=Inputs!$B$15,Inputs!$B$14,0) -> 0 | J6: =$C6*IF($A6<1,0,Inputs!$B$5*(1-Inputs!$B$10)^($A6-1)*Inputs!$B$7*(1+Inputs!$B$12)^($A6-1)*(1-IF($A6=Inputs!$B$15,Inputs!$B$17/12,0))) -> 148127.85 | K6: =J6*Inputs!$B$18-F6-G6-H6-I6 -> 137627.85 | L6: =$C6*IF($A6=0,Inputs!$B$8*Inputs!$B$6*1000,0) -> 0 | M6: =$C6*IF($A6>=1,Inputs!$B$9*Inputs!$B$6,0) -> 10500 | N6: =0 -> 0 | O6: =$C6*IF($A6=0,Inputs!$B$14,0) -> 0 | P6: =$C6*IF($A6<1,0,Inputs!$B$5*(1-Inputs!$B$10)^($A6-1)*Inputs!$B$7*(1+Inputs!$B$12)^($A6-1)) -> 148127.85 | Q6: =P6*Inputs!$B$18-L6-M6-N6-O6 -> 137627.85 | R6: =$C6*IF($A6=Inputs!$B$15,Inputs!$B$8*Inputs!$B$6*1000,0) -> 0 | S6: =$C6*IF($A6>Inputs!$B$15,Inputs!$B$9*Inputs!$B$6,0) -> 0 | T6: =0 -> 0 | U6: =$C6*IF($A6=Inputs!$B$15,Inputs!$B$14,0) -> 0 | V6: =$C6*IF($A6<=Inputs!$B$15,0,Inputs!$B$5*(1-Inputs!$B$10)^($A6-Inputs!$B$15-1)*Inputs!$B$7*(1+Inputs!$B$12)^($A6-1)) -> 0 | W6: =V6*Inputs!$B$18-R6-S6-T6-U6 -> 0
A7: 2 | B7: =1/(1+Inputs!$B$11)^$A7 -> 0.8767131 | C7: =IF($A7<=Inputs!$B$13,1,0) -> 1 | D7: =$C7*IF($A7=Inputs!$B$15,Inputs!$B$14,0) -> 0 | E7: =-D7 -> 0 | F7: =$C7*IF($A7=0,Inputs!$B$8*Inputs!$B$6*1000,0) -> 0 | G7: =$C7*IF($A7>=1,Inputs!$B$9*Inputs!$B$6,0) -> 10500 | H7: =$C7*IF($A7=Inputs!$B$15,Inputs!$B$16,0) -> 0 | I7: =$C7*IF($A7=Inputs!$B$15,Inputs!$B$14,0) -> 0 | J7: =$C7*IF($A7<1,0,Inputs!$B$5*(1-Inputs!$B$10)^($A7-1)*Inputs!$B$7*(1+Inputs!$B$12)^($A7-1)*(1-IF($A7=Inputs!$B$15,Inputs!$B$17/12,0))) -> 147090.95 | K7: =J7*Inputs!$B$18-F7-G7-H7-I7 -> 136590.95 | L7: =$C7*IF($A7=0,Inputs!$B$8*Inputs!$B$6*1000,0) -> 0 | M7: =$C7*IF($A7>=1,Inputs!$B$9*Inputs!$B$6,0) -> 10500 | N7: =0 -> 0 | O7: =$C7*IF($A7=0,Inputs!$B$14,0) -> 0 | P7: =$C7*IF($A7<1,0,Inputs!$B$5*(1-Inputs!$B$10)^($A7-1)*Inputs!$B$7*(1+Inputs!$B$12)^($A7-1)) -> 147090.95 | Q7: =P7*Inputs!$B$18-L7-M7-N7-O7 -> 136590.95 | R7: =$C7*IF($A7=Inputs!$B$15,Inputs!$B$8*Inputs!$B$6*1000,0) -> 0 | S7: =$C7*IF($A7>Inputs!$B$15,Inputs!$B$9*Inputs!$B$6,0) -> 0 | T7: =0 -> 0 | U7: =$C7*IF($A7=Inputs!$B$15,Inputs!$B$14,0) -> 0 | V7: =$C7*IF($A7<=Inputs!$B$15,0,Inputs!$B$5*(1-Inputs!$B$10)^($A7-Inputs!$B$15-1)*Inputs!$B$7*(1+Inputs!$B$12)^($A7-1)) -> 0 | W7: =V7*Inputs!$B$18-R7-S7-T7-U7 -> 0
A8: 3 | B8: =1/(1+Inputs!$B$11)^$A8 -> 0.82089241 | C8: =IF($A8<=Inputs!$B$13,1,0) -> 1 | D8: =$C8*IF($A8=Inputs!$B$15,Inputs!$B$14,0) -> 500000 | E8: =-D8 -> -500000 | F8: =$C8*IF($A8=0,Inputs!$B$8*Inputs!$B$6*1000,0) -> 0 | G8: =$C8*IF($A8>=1,Inputs!$B$9*Inputs!$B$6,0) -> 10500 | H8: =$C8*IF($A8=Inputs!$B$15,Inputs!$B$16,0) -> 75000 | I8: =$C8*IF($A8=Inputs!$B$15,Inputs!$B$14,0) -> 500000 | J8: =$C8*IF($A8<1,0,Inputs!$B$5*(1-Inputs!$B$10)^($A8-1)*Inputs!$B$7*(1+Inputs!$B$12)^($A8-1)*(1-IF($A8=Inputs!$B$15,Inputs!$B$17/12,0))) -> 121717.76 | K8: =J8*Inputs!$B$18-F8-G8-H8-I8 -> -463782.24 | L8: =$C8*IF($A8=0,Inputs!$B$8*Inputs!$B$6*1000,0) -> 0 | M8: =$C8*IF($A8>=1,Inputs!$B$9*Inputs!$B$6,0) -> 10500 | N8: =0 -> 0 | O8: =$C8*IF($A8=0,Inputs!$B$14,0) -> 0 | P8: =$C8*IF($A8<1,0,Inputs!$B$5*(1-Inputs!$B$10)^($A8-1)*Inputs!$B$7*(1+Inputs!$B$12)^($A8-1)) -> 146061.32 | Q8: =P8*Inputs!$B$18-L8-M8-N8-O8 -> 135561.32 | R8: =$C8*IF($A8=Inputs!$B$15,Inputs!$B$8*Inputs!$B$6*1000,0) -> 1065000 | S8: =$C8*IF($A8>Inputs!$B$15,Inputs!$B$9*Inputs!$B$6,0) -> 0 | T8: =0 -> 0 | U8: =$C8*IF($A8=Inputs!$B$15,Inputs!$B$14,0) -> 500000 | V8: =$C8*IF($A8<=Inputs!$B$15,0,Inputs!$B$5*(1-Inputs!$B$10)^($A8-Inputs!$B$15-1)*Inputs!$B$7*(1+Inputs!$B$12)^($A8-1)) -> 0 | W8: =V8*Inputs!$B$18-R8-S8-T8-U8 -> -1565000
A9: 4 | B9: =1/(1+Inputs!$B$11)^$A9 -> 0.76862586 | C9: =IF($A9<=Inputs!$B$13,1,0) -> 1 | D9: =$C9*IF($A9=Inputs!$B$15,Inputs!$B$14,0) -> 0 | E9: =-D9 -> 0 | F9: =$C9*IF($A9=0,Inputs!$B$8*Inputs!$B$6*1000,0) -> 0 | G9: =$C9*IF($A9>=1,Inputs!$B$9*Inputs!$B$6,0) -> 10500 | H9: =$C9*IF($A9=Inputs!$B$15,Inputs!$B$16,0) -> 0 | I9: =$C9*IF($A9=Inputs!$B$15,Inputs!$B$14,0) -> 0 | J9: =$C9*IF($A9<1,0,Inputs!$B$5*(1-Inputs!$B$10)^($A9-1)*Inputs!$B$7*(1+Inputs!$B$12)^($A9-1)*(1-IF($A9=Inputs!$B$15,Inputs!$B$17/12,0))) -> 145038.89 | K9: =J9*Inputs!$B$18-F9-G9-H9-I9 -> 134538.89 | L9: =$C9*IF($A9=0,Inputs!$B$8*Inputs!$B$6*1000,0) -> 0 | M9: =$C9*IF($A9>=1,Inputs!$B$9*Inputs!$B$6,0) -> 10500 | N9: =0 -> 0 | O9: =$C9*IF($A9=0,Inputs!$B$14,0) -> 0 | P9: =$C9*IF($A9<1,0,Inputs!$B$5*(1-Inputs!$B$10)^($A9-1)*Inputs!$B$7*(1+Inputs!$B$12)^($A9-1)) -> 145038.89 | Q9: =P9*Inputs!$B$18-L9-M9-N9-O9 -> 134538.89 | R9: =$C9*IF($A9=Inputs!$B$15,Inputs!$B$8*Inputs!$B$6*1000,0) -> 0 | S9: =$C9*IF($A9>Inputs!$B$15,Inputs!$B$9*Inputs!$B$6,0) -> 10500 | T9: =0 -> 0 | U9: =$C9*IF($A9=Inputs!$B$15,Inputs!$B$14,0) -> 0 | V9: =$C9*IF($A9<=Inputs!$B$15,0,Inputs!$B$5*(1-Inputs!$B$10)^($A9-Inputs!$B$15-1)*Inputs!$B$7*(1+Inputs!$B$12)^($A9-1)) -> 148127.85 | W9: =V9*Inputs!$B$18-R9-S9-T9-U9 -> 137627.85
A10: 5 | B10: =1/(1+Inputs!$B$11)^$A10 -> 0.71968713 | C10: =IF($A10<=Inputs!$B$13,1,0) -> 1 | D10: =$C10*IF($A10=Inputs!$B$15,Inputs!$B$14,0) -> 0 | E10: =-D10 -> 0 | F10: =$C10*IF($A10=0,Inputs!$B$8*Inputs!$B$6*1000,0) -> 0 | G10: =$C10*IF($A10>=1,Inputs!$B$9*Inputs!$B$6,0) -> 10500 | H10: =$C10*IF($A10=Inputs!$B$15,Inputs!$B$16,0) -> 0 | I10: =$C10*IF($A10=Inputs!$B$15,Inputs!$B$14,0) -> 0 | J10: =$C10*IF($A10<1,0,Inputs!$B$5*(1-Inputs!$B$10)^($A10-1)*Inputs!$B$7*(1+Inputs!$B$12)^($A10-1)*(1-IF($A10=Inputs!$B$15,Inputs!$B$17/12,0))) -> 144023.62 | K10: =J10*Inputs!$B$18-F10-G10-H10-I10 -> 133523.62 | L10: =$C10*IF($A10=0,Inputs!$B$8*Inputs!$B$6*1000,0) -> 0 | M10: =$C10*IF($A10>=1,Inputs!$B$9*Inputs!$B$6,0) -> 10500 | N10: =0 -> 0 | O10: =$C10*IF($A10=0,Inputs!$B$14,0) -> 0 | P10: =$C10*IF($A10<1,0,Inputs!$B$5*(1-Inputs!$B$10)^($A10-1)*Inputs!$B$7*(1+Inputs!$B$12)^($A10-1)) -> 144023.62 | Q10: =P10*Inputs!$B$18-L10-M10-N10-O10 -> 133523.62 | R10: =$C10*IF($A10=Inputs!$B$15,Inputs!$B$8*Inputs!$B$6*1000,0) -> 0 | S10: =$C10*IF($A10>Inputs!$B$15,Inputs!$B$9*Inputs!$B$6,0) -> 10500 | T10: =0 -> 0 | U10: =$C10*IF($A10=Inputs!$B$15,Inputs!$B$14,0) -> 0 | V10: =$C10*IF($A10<=Inputs!$B$15,0,Inputs!$B$5*(1-Inputs!$B$10)^($A10-Inputs!$B$15-1)*Inputs!$B$7*(1+Inputs!$B$12)^($A10-1)) -> 147090.95 | W10: =V10*Inputs!$B$18-R10-S10-T10-U10 -> 136590.95
A11: 6 | B11: =1/(1+Inputs!$B$11)^$A11 -> 0.67386435 | C11: =IF($A11<=Inputs!$B$13,1,0) -> 1 | D11: =$C11*IF($A11=Inputs!$B$15,Inputs!$B$14,0) -> 0 | E11: =-D11 -> 0 | F11: =$C11*IF($A11=0,Inputs!$B$8*Inputs!$B$6*1000,0) -> 0 | G11: =$C11*IF($A11>=1,Inputs!$B$9*Inputs!$B$6,0) -> 10500 | H11: =$C11*IF($A11=Inputs!$B$15,Inputs!$B$16,0) -> 0 | I11: =$C11*IF($A11=Inputs!$B$15,Inputs!$B$14,0) -> 0 | J11: =$C11*IF($A11<1,0,Inputs!$B$5*(1-Inputs!$B$10)^($A11-1)*Inputs!$B$7*(1+Inputs!$B$12)^($A11-1)*(1-IF($A11=Inputs!$B$15,Inputs!$B$17/12,0))) -> 143015.45 | K11: =J11*Inputs!$B$18-F11-G11-H11-I11 -> 132515.45 | L11: =$C11*IF($A11=0,Inputs!$B$8*Inputs!$B$6*1000,0) -> 0 | M11: =$C11*IF($A11>=1,Inputs!$B$9*Inputs!$B$6,0) -> 10500 | N11: =0 -> 0 | O11: =$C11*IF($A11=0,Inputs!$B$14,0) -> 0 | P11: =$C11*IF($A11<1,0,Inputs!$B$5*(1-Inputs!$B$10)^($A11-1)*Inputs!$B$7*(1+Inputs!$B$12)^($A11-1)) -> 143015.45 | Q11: =P11*Inputs!$B$18-L11-M11-N11-O11 -> 132515.45 | R11: =$C11*IF($A11=Inputs!$B$15,Inputs!$B$8*Inputs!$B$6*1000,0) -> 0 | S11: =$C11*IF($A11>Inputs!$B$15,Inputs!$B$9*Inputs!$B$6,0) -> 10500 | T11: =0 -> 0 | U11: =$C11*IF($A11=Inputs!$B$15,Inputs!$B$14,0) -> 0 | V11: =$C11*IF($A11<=Inputs!$B$15,0,Inputs!$B$5*(1-Inputs!$B$10)^($A11-Inputs!$B$15-1)*Inputs!$B$7*(1+Inputs!$B$12)^($A11-1)) -> 146061.32 | W11: =V11*Inputs!$B$18-R11-S11-T11-U11 -> 135561.32
A12: 7 | B12: =1/(1+Inputs!$B$11)^$A12 -> 0.63095913 | C12: =IF($A12<=Inputs!$B$13,1,0) -> 1 | D12: =$C12*IF($A12=Inputs!$B$15,Inputs!$B$14,0) -> 0 | E12: =-D12 -> 0 | F12: =$C12*IF($A12=0,Inputs!$B$8*Inputs!$B$6*1000,0) -> 0 | G12: =$C12*IF($A12>=1,Inputs!$B$9*Inputs!$B$6,0) -> 10500 | H12: =$C12*IF($A12=Inputs!$B$15,Inputs!$B$16,0) -> 0 | I12: =$C12*IF($A12=Inputs!$B$15,Inputs!$B$14,0) -> 0 | J12: =$C12*IF($A12<1,0,Inputs!$B$5*(1-Inputs!$B$10)^($A12-1)*Inputs!$B$7*(1+Inputs!$B$12)^($A12-1)*(1-IF($A12=Inputs!$B$15,Inputs!$B$17/12,0))) -> 142014.34 | K12: =J12*Inputs!$B$18-F12-G12-H12-I12 -> 131514.34 | L12: =$C12*IF($A12=0,Inputs!$B$8*Inputs!$B$6*1000,0) -> 0 | M12: =$C12*IF($A12>=1,Inputs!$B$9*Inputs!$B$6,0) -> 10500 | N12: =0 -> 0 | O12: =$C12*IF($A12=0,Inputs!$B$14,0) -> 0 | P12: =$C12*IF($A12<1,0,Inputs!$B$5*(1-Inputs!$B$10)^($A12-1)*Inputs!$B$7*(1+Inputs!$B$12)^($A12-1)) -> 142014.34 | Q12: =P12*Inputs!$B$18-L12-M12-N12-O12 -> 131514.34 | R12: =$C12*IF($A12=Inputs!$B$15,Inputs!$B$8*Inputs!$B$6*1000,0) -> 0 | S12: =$C12*IF($A12>Inputs!$B$15,Inputs!$B$9*Inputs!$B$6,0) -> 10500 | T12: =0 -> 0 | U12: =$C12*IF($A12=Inputs!$B$15,Inputs!$B$14,0) -> 0 | V12: =$C12*IF($A12<=Inputs!$B$15,0,Inputs!$B$5*(1-Inputs!$B$10)^($A12-Inputs!$B$15-1)*Inputs!$B$7*(1+Inputs!$B$12)^($A12-1)) -> 145038.89 | W12: =V12*Inputs!$B$18-R12-S12-T12-U12 -> 134538.89
A13: 8 | B13: =1/(1+Inputs!$B$11)^$A13 -> 0.59078571 | C13: =IF($A13<=Inputs!$B$13,1,0) -> 1 | D13: =$C13*IF($A13=Inputs!$B$15,Inputs!$B$14,0) -> 0 | E13: =-D13 -> 0 | F13: =$C13*IF($A13=0,Inputs!$B$8*Inputs!$B$6*1000,0) -> 0 | G13: =$C13*IF($A13>=1,Inputs!$B$9*Inputs!$B$6,0) -> 10500 | H13: =$C13*IF($A13=Inputs!$B$15,Inputs!$B$16,0) -> 0 | I13: =$C13*IF($A13=Inputs!$B$15,Inputs!$B$14,0) -> 0 | J13: =$C13*IF($A13<1,0,Inputs!$B$5*(1-Inputs!$B$10)^($A13-1)*Inputs!$B$7*(1+Inputs!$B$12)^($A13-1)*(1-IF($A13=Inputs!$B$15,Inputs!$B$17/12,0))) -> 141020.24 | K13: =J13*Inputs!$B$18-F13-G13-H13-I13 -> 130520.24 | L13: =$C13*IF($A13=0,Inputs!$B$8*Inputs!$B$6*1000,0) -> 0 | M13: =$C13*IF($A13>=1,Inputs!$B$9*Inputs!$B$6,0) -> 10500 | N13: =0 -> 0 | O13: =$C13*IF($A13=0,Inputs!$B$14,0) -> 0 | P13: =$C13*IF($A13<1,0,Inputs!$B$5*(1-Inputs!$B$10)^($A13-1)*Inputs!$B$7*(1+Inputs!$B$12)^($A13-1)) -> 141020.24 | Q13: =P13*Inputs!$B$18-L13-M13-N13-O13 -> 130520.24 | R13: =$C13*IF($A13=Inputs!$B$15,Inputs!$B$8*Inputs!$B$6*1000,0) -> 0 | S13: =$C13*IF($A13>Inputs!$B$15,Inputs!$B$9*Inputs!$B$6,0) -> 10500 | T13: =0 -> 0 | U13: =$C13*IF($A13=Inputs!$B$15,Inputs!$B$14,0) -> 0 | V13: =$C13*IF($A13<=Inputs!$B$15,0,Inputs!$B$5*(1-Inputs!$B$10)^($A13-Inputs!$B$15-1)*Inputs!$B$7*(1+Inputs!$B$12)^($A13-1)) -> 144023.62 | W13: =V13*Inputs!$B$18-R13-S13-T13-U13 -> 133523.62
A14: 9 | B14: =1/(1+Inputs!$B$11)^$A14 -> 0.55317014 | C14: =IF($A14<=Inputs!$B$13,1,0) -> 1 | D14: =$C14*IF($A14=Inputs!$B$15,Inputs!$B$14,0) -> 0 | E14: =-D14 -> 0 | F14: =$C14*IF($A14=0,Inputs!$B$8*Inputs!$B$6*1000,0) -> 0 | G14: =$C14*IF($A14>=1,Inputs!$B$9*Inputs!$B$6,0) -> 10500 | H14: =$C14*IF($A14=Inputs!$B$15,Inputs!$B$16,0) -> 0 | I14: =$C14*IF($A14=Inputs!$B$15,Inputs!$B$14,0) -> 0 | J14: =$C14*IF($A14<1,0,Inputs!$B$5*(1-Inputs!$B$10)^($A14-1)*Inputs!$B$7*(1+Inputs!$B$12)^($A14-1)*(1-IF($A14=Inputs!$B$15,Inputs!$B$17/12,0))) -> 140033.1 | K14: =J14*Inputs!$B$18-F14-G14-H14-I14 -> 129533.1 | L14: =$C14*IF($A14=0,Inputs!$B$8*Inputs!$B$6*1000,0) -> 0 | M14: =$C14*IF($A14>=1,Inputs!$B$9*Inputs!$B$6,0) -> 10500 | N14: =0 -> 0 | O14: =$C14*IF($A14=0,Inputs!$B$14,0) -> 0 | P14: =$C14*IF($A14<1,0,Inputs!$B$5*(1-Inputs!$B$10)^($A14-1)*Inputs!$B$7*(1+Inputs!$B$12)^($A14-1)) -> 140033.1 | Q14: =P14*Inputs!$B$18-L14-M14-N14-O14 -> 129533.1 | R14: =$C14*IF($A14=Inputs!$B$15,Inputs!$B$8*Inputs!$B$6*1000,0) -> 0 | S14: =$C14*IF($A14>Inputs!$B$15,Inputs!$B$9*Inputs!$B$6,0) -> 10500 | T14: =0 -> 0 | U14: =$C14*IF($A14=Inputs!$B$15,Inputs!$B$14,0) -> 0 | V14: =$C14*IF($A14<=Inputs!$B$15,0,Inputs!$B$5*(1-Inputs!$B$10)^($A14-Inputs!$B$15-1)*Inputs!$B$7*(1+Inputs!$B$12)^($A14-1)) -> 143015.45 | W14: =V14*Inputs!$B$18-R14-S14-T14-U14 -> 132515.45
A15: 10 | B15: =1/(1+Inputs!$B$11)^$A15 -> 0.51794957 | C15: =IF($A15<=Inputs!$B$13,1,0) -> 1 | D15: =$C15*IF($A15=Inputs!$B$15,Inputs!$B$14,0) -> 0 | E15: =-D15 -> 0 | F15: =$C15*IF($A15=0,Inputs!$B$8*Inputs!$B$6*1000,0) -> 0 | G15: =$C15*IF($A15>=1,Inputs!$B$9*Inputs!$B$6,0) -> 10500 | H15: =$C15*IF($A15=Inputs!$B$15,Inputs!$B$16,0) -> 0 | I15: =$C15*IF($A15=Inputs!$B$15,Inputs!$B$14,0) -> 0 | J15: =$C15*IF($A15<1,0,Inputs!$B$5*(1-Inputs!$B$10)^($A15-1)*Inputs!$B$7*(1+Inputs!$B$12)^($A15-1)*(1-IF($A15=Inputs!$B$15,Inputs!$B$17/12,0))) -> 139052.87 | K15: =J15*Inputs!$B$18-F15-G15-H15-I15 -> 128552.87 | L15: =$C15*IF($A15=0,Inputs!$B$8*Inputs!$B$6*1000,0) -> 0 | M15: =$C15*IF($A15>=1,Inputs!$B$9*Inputs!$B$6,0) -> 10500 | N15: =0 -> 0 | O15: =$C15*IF($A15=0,Inputs!$B$14,0) -> 0 | P15: =$C15*IF($A15<1,0,Inputs!$B$5*(1-Inputs!$B$10)^($A15-1)*Inputs!$B$7*(1+Inputs!$B$12)^($A15-1)) -> 139052.87 | Q15: =P15*Inputs!$B$18-L15-M15-N15-O15 -> 128552.87 | R15: =$C15*IF($A15=Inputs!$B$15,Inputs!$B$8*Inputs!$B$6*1000,0) -> 0 | S15: =$C15*IF($A15>Inputs!$B$15,Inputs!$B$9*Inputs!$B$6,0) -> 10500 | T15: =0 -> 0 | U15: =$C15*IF($A15=Inputs!$B$15,Inputs!$B$14,0) -> 0 | V15: =$C15*IF($A15<=Inputs!$B$15,0,Inputs!$B$5*(1-Inputs!$B$10)^($A15-Inputs!$B$15-1)*Inputs!$B$7*(1+Inputs!$B$12)^($A15-1)) -> 142014.34 | W15: =V15*Inputs!$B$18-R15-S15-T15-U15 -> 131514.34
A16: 11 | B16: =1/(1+Inputs!$B$11)^$A16 -> 0.4849715 | C16: =IF($A16<=Inputs!$B$13,1,0) -> 1 | D16: =$C16*IF($A16=Inputs!$B$15,Inputs!$B$14,0) -> 0 | E16: =-D16 -> 0 | F16: =$C16*IF($A16=0,Inputs!$B$8*Inputs!$B$6*1000,0) -> 0 | G16: =$C16*IF($A16>=1,Inputs!$B$9*Inputs!$B$6,0) -> 10500 | H16: =$C16*IF($A16=Inputs!$B$15,Inputs!$B$16,0) -> 0 | I16: =$C16*IF($A16=Inputs!$B$15,Inputs!$B$14,0) -> 0 | J16: =$C16*IF($A16<1,0,Inputs!$B$5*(1-Inputs!$B$10)^($A16-1)*Inputs!$B$7*(1+Inputs!$B$12)^($A16-1)*(1-IF($A16=Inputs!$B$15,Inputs!$B$17/12,0))) -> 138079.5 | K16: =J16*Inputs!$B$18-F16-G16-H16-I16 -> 127579.5 | L16: =$C16*IF($A16=0,Inputs!$B$8*Inputs!$B$6*1000,0) -> 0 | M16: =$C16*IF($A16>=1,Inputs!$B$9*Inputs!$B$6,0) -> 10500 | N16: =0 -> 0 | O16: =$C16*IF($A16=0,Inputs!$B$14,0) -> 0 | P16: =$C16*IF($A16<1,0,Inputs!$B$5*(1-Inputs!$B$10)^($A16-1)*Inputs!$B$7*(1+Inputs!$B$12)^($A16-1)) -> 138079.5 | Q16: =P16*Inputs!$B$18-L16-M16-N16-O16 -> 127579.5 | R16: =$C16*IF($A16=Inputs!$B$15,Inputs!$B$8*Inputs!$B$6*1000,0) -> 0 | S16: =$C16*IF($A16>Inputs!$B$15,Inputs!$B$9*Inputs!$B$6,0) -> 10500 | T16: =0 -> 0 | U16: =$C16*IF($A16=Inputs!$B$15,Inputs!$B$14,0) -> 0 | V16: =$C16*IF($A16<=Inputs!$B$15,0,Inputs!$B$5*(1-Inputs!$B$10)^($A16-Inputs!$B$15-1)*Inputs!$B$7*(1+Inputs!$B$12)^($A16-1)) -> 141020.24 | W16: =V16*Inputs!$B$18-R16-S16-T16-U16 -> 130520.24
... A35: 30 | B35: =1/(1+Inputs!$B$11)^$A35 -> 0.13895124 | C35: =IF($A35<=Inputs!$B$13,1,0) -> 0 | D35: =$C35*IF($A35=Inputs!$B$15,Inputs!$B$14,0) -> 0 | E35: =-D35 -> 0 | F35: =$C35*IF($A35=0,Inputs!$B$8*Inputs!$B$6*1000,0) -> 0 | G35: =$C35*IF($A35>=1,Inputs!$B$9*Inputs!$B$6,0) -> 0 | H35: =$C35*IF($A35=Inputs!$B$15,Inputs!$B$16,0) -> 0 | I35: =$C35*IF($A35=Inputs!$B$15,Inputs!$B$14,0) -> 0 | J35: =$C35*IF($A35<1,0,Inputs!$B$5*(1-Inputs!$B$10)^($A35-1)*Inputs!$B$7*(1+Inputs!$B$12)^($A35-1)*(1-IF($A35=Inputs!$B$15,Inputs!$B$17/12,0))) -> 0 | K35: =J35*Inputs!$B$18-F35-G35-H35-I35 -> 0 | L35: =$C35*IF($A35=0,Inputs!$B$8*Inputs!$B$6*1000,0) -> 0 | M35: =$C35*IF($A35>=1,Inputs!$B$9*Inputs!$B$6,0) -> 0 | N35: =0 -> 0 | O35: =$C35*IF($A35=0,Inputs!$B$14,0) -> 0 | P35: =$C35*IF($A35<1,0,Inputs!$B$5*(1-Inputs!$B$10)^($A35-1)*Inputs!$B$7*(1+Inputs!$B$12)^($A35-1)) -> 0 | Q35: =P35*Inputs!$B$18-L35-M35-N35-O35 -> 0 | R35: =$C35*IF($A35=Inputs!$B$15,Inputs!$B$8*Inputs!$B$6*1000,0) -> 0 | S35: =$C35*IF($A35>Inputs!$B$15,Inputs!$B$9*Inputs!$B$6,0) -> 0 | T35: =0 -> 0 | U35: =$C35*IF($A35=Inputs!$B$15,Inputs!$B$14,0) -> 0 | V35: =$C35*IF($A35<=Inputs!$B$15,0,Inputs!$B$5*(1-Inputs!$B$10)^($A35-Inputs!$B$15-1)*Inputs!$B$7*(1+Inputs!$B$12)^($A35-1)) -> 0 | W35: =V35*Inputs!$B$18-R35-S35-T35-U35 -> 0
A36: Present value | D36: =SUMPRODUCT(D5:D35,$B$5:$B$35) -> 410446.21 | E36: =SUMPRODUCT(E5:E35,$B$5:$B$35) -> -410446.21 | F36: =SUMPRODUCT(F5:F35,$B$5:$B$35) -> 1065000 | G36: =SUMPRODUCT(G5:G35,$B$5:$B$35) -> 124599.22 | H36: =SUMPRODUCT(H5:H35,$B$5:$B$35) -> 61566.931 | I36: =SUMPRODUCT(I5:I35,$B$5:$B$35) -> 410446.21 | J36: =SUMPRODUCT(J5:J35,$B$5:$B$35) -> 1635146.4 | K36: =SUMPRODUCT(K5:K35,$B$5:$B$35) -> -26465.992 | ... W36: =SUMPRODUCT(W5:W35,$B$5:$B$35) -> -87067.246

Sheet Reference
A1: Primary reference figures behind the sourced inputs
A2: From the EIA table you uploaded and the NREL/NLR report. 'Value used in model' links to Inputs.
A4: Figure | B4: Value | C4: Unit | D4: Value in model units | E4: Value used in model | F4: Difference (model - reference) | G4: Related input | H4: Source | I4: Link | J4: Caveat
A5: MA commercial avg price, Aug 2026 (prelim.) | B5: 24.11 | C5: cents/kWh | D5: =IF(OR(C5="cents/kWh",C5="percent"),B5/100,B5) -> 0.2411 | E5: =Inputs!B7 -> 0.2411 | F5: =E5-D5 -> 0 | G5: electricityValuePerKwh | H5: EIA Electric Power Monthly Table 5.6.A | I5: https://www.eia.gov/electricity/monthly/xls/table_5_06_a.xlsx | J5: Single month; preliminary estimate.
A6: MA commercial avg price, Aug 2025 (final) | B6: 23.15 | C6: cents/kWh | D6: =IF(OR(C6="cents/kWh",C6="percent"),B6/100,B6) -> 0.2315 | E6: =Inputs!B7 -> 0.2411 | F6: =E6-D6 -> 0.0096 | G6: electricityValuePerKwh | H6: EIA Electric Power Monthly Table 5.6.A | I6: https://www.eia.gov/electricity/monthly/xls/table_5_06_a.xlsx | J6: Single month; final value.
A7: U.S. commercial avg price, Aug 2026 (prelim.) | B7: 14.47 | C7: cents/kWh | D7: =IF(OR(C7="cents/kWh",C7="percent"),B7/100,B7) -> 0.1447 | E7: =Inputs!B7 -> 0.2411 | F7: =E7-D7 -> 0.0964 | G7: electricityValuePerKwh | H7: EIA Electric Power Monthly Table 5.6.A | I7: https://www.eia.gov/electricity/monthly/xls/table_5_06_a.xlsx | J7: National figure; shows how high Massachusetts is.
A8: Commercial PV rooftop (200 kWdc), Q1 2021 | B8: 1.89 | C8: $/Wdc | D8: =IF(OR(C8="cents/kWh",C8="percent"),B8/100,B8) -> 1.89 | E8: =Inputs!B8 -> 2.13 | F8: =E8-D8 -> 0.24 | G8: solarCapexPerWatt | H8: NREL/NLR TP-7A40-92536, Table A-1 | I8: https://docs.nlr.gov/docs/fy25osti/92536.pdf | J8: 2024 USD.
A9: Commercial PV rooftop (200 kWdc), Q1 2022 MMP | B9: 2.13 | C9: $/Wdc | D9: =IF(OR(C9="cents/kWh",C9="percent"),B9/100,B9) -> 2.13 | E9: =Inputs!B8 -> 2.13 | F9: =E9-D9 -> 0 | G9: solarCapexPerWatt | H9: NREL/NLR TP-7A40-92536, Table A-1 | I9: https://docs.nlr.gov/docs/fy25osti/92536.pdf | J9: 2024 USD. Used in the model.
A10: Commercial PV ground-mount (3 MWdc), Q1 2024 MMP | B10: 1.55 | C10: $/Wdc | D10: =IF(OR(C10="cents/kWh",C10="percent"),B10/100,B10) -> 1.55 | E10: =Inputs!B8 -> 2.13 | F10: =E10-D10 -> 0.58 | G10: solarCapexPerWatt | H10: NREL/NLR TP-7A40-92536, Table A-1 | I10: https://docs.nlr.gov/docs/fy25osti/92536.pdf | J10: NOT comparable to a rooftop: different mounting and system size.
A11: Commercial PV O&M, 2022 (200 kWdc rooftop) | B11: 21 | C11: $/kWdc-yr | D11: =IF(OR(C11="cents/kWh",C11="percent"),B11/100,B11) -> 21 | E11: =Inputs!B9 -> 21 | F11: =E11-D11 -> 0 | G11: omPerKwYear | H11: NREL/NLR TP-7A40-92536, Table A-7 | I11: https://docs.nlr.gov/docs/fy25osti/92536.pdf | J11: Used in the model.
A12: Commercial PV O&M, 2024 (3 MWdc ground-mount) | B12: 20 | C12: $/kWdc-yr | D12: =IF(OR(C12="cents/kWh",C12="percent"),B12/100,B12) -> 20 | E12: =Inputs!B9 -> 21 | F12: =E12-D12 -> 1 | G12: omPerKwYear | H12: NREL/NLR TP-7A40-92536, Table A-7 | I12: https://docs.nlr.gov/docs/fy25osti/92536.pdf | J12: Different system type.
A13: Commercial PV annual degradation | B13: 0.7 | C13: percent | D13: =IF(OR(C13="cents/kWh",C13="percent"),B13/100,B13) -> 0.007 | E13: =Inputs!B10 -> 0.007 | F13: =E13-D13 -> 0 | G13: degradationRate | H13: NREL/NLR TP-7A40-92536, Table A-7 | I13: https://docs.nlr.gov/docs/fy25osti/92536.pdf | J13: Same 0.70% in every recent year.
A14: Commercial PV equity discount rate (real), 2022 | B14: 6.1 | C14: percent | D14: =IF(OR(C14="cents/kWh",C14="percent"),B14/100,B14) -> 0.061 | E14: =Inputs!B11 -> 0.068 | F14: =E14-D14 -> 0.007 | G14: discountRate | H14: NREL/NLR TP-7A40-92536, Table A-7 | I14: https://docs.nlr.gov/docs/fy25osti/92536.pdf | J14: Real rate.
A15: Commercial PV equity discount rate (real), 2023-24 | B15: 6.8 | C15: percent | D15: =IF(OR(C15="cents/kWh",C15="percent"),B15/100,B15) -> 0.068 | E15: =Inputs!B11 -> 0.068 | F15: =E15-D15 -> 0 | G15: discountRate | H15: NREL/NLR TP-7A40-92536, Table A-7 | I15: https://docs.nlr.gov/docs/fy25osti/92536.pdf | J15: Real rate. Used in the model.
